plover_textarea/__init__.py
plover_textarea/config.py
plover_textarea/extension.py
plover_textarea/py.typed
plover_textarea-0.0.2.dist-info/LICENSE
plover_textarea-0.0.2.dist-info/METADATA
plover_textarea-0.0.2.dist-info/WHEEL
plover_textarea-0.0.2.dist-info/entry_points.txt
plover_textarea-0.0.2.dist-info/top_level.txt
plover_textarea-0.0.2.dist-info/zip-safe
plover_textarea-0.0.2.dist-info/RECORD
